For Simulate/exp/TB_fakeMul.v

`include"../FakeMul.v"
module test;
	reg signed[8-1:0]counter;
	 XMul#(.dataW(8)) xm(counter,8'd127,XZZ);
	 
	 reg clk;
	 always #5 clk=~clk;
	 always@(posedge clk)counter=counter+1;
   initial begin
        $dumpfile("wave.vcd");$dumpvars;
       clk=0;
		counter=0;
       #3500 $finish;
    end
endmodule

For Simulate/FakeMul.v
module ABSData
#(parameter
dataW=8,
outW=dataW-1
)
(
input signed[dataW-1:0]in,
output signed[outW-1:0]outData
);
	assign outData=(in[dataW-1])?-in:in;
endmodule


module XMul
#(parameter
dataW=8,
outW=dataW,
power=1
)
(
input signed[dataW-1:0]in1,
input signed[dataW-1:0]in2,
output signed[outW-1:0]outData
);
parameter tableDataW=outW-1;//its unsigned
localparam tableDataMax=(2**tableDataW)-1;
parameter tableLW=dataW-1;
localparam tableL=(2**tableLW);

localparam FixTableL=128;
localparam FixTableBitW=$clog2(FixTableL);
localparam FixTableMax=FixTableL-1;

wire [FixTableBitW*FixTableL-1:0]sqTableS={7'd127,7'd127,7'd127,7'd127,7'd127,7'd127,7'd127,7'd127,7'd127,7'd127,7'd127,7'd127,7'd127,7'd127,7'd127,7'd127,7'd127,7'd127,7'd127,7'd127,7'd127,7'd127,7'd127,7'd127,7'd127,7'd127,7'd127,7'd127,7'd127,7'd127,7'd127,7'd127,7'd127,7'd127,7'd127,7'd127,7'd126,7'd126,7'd126,7'd126,7'd126,7'd126,7'd126,7'd125,7'd125,7'd125,7'd125,7'd124,7'd124,7'd124,7'd123,7'd123,7'd122,7'd121,7'd121,7'd120,7'd119,7'd118,7'd117,7'd116,7'd115,7'd113,7'd112,7'd111,7'd109,7'd107,7'd106,7'd104,7'd102,7'd100,7'd97,7'd95,7'd93,7'd90,7'd88,7'd85,7'd83,7'd80,7'd77,7'd75,7'd72,7'd69,7'd66,7'd63,7'd60,7'd57,7'd54,7'd52,7'd49,7'd46,7'd43,7'd41,7'd38,7'd36,7'd33,7'd31,7'd29,7'd27,7'd24,7'd23,7'd21,7'd19,7'd17,7'd16,7'd14,7'd13,7'd12,7'd10,7'd9,7'd8,7'd7,7'd6,7'd6,7'd5,7'd4,7'd4,7'd3,7'd3,7'd2,7'd2,7'd2,7'd1,7'd1,7'd1,7'd0,7'd0,7'd0,7'd0};
wire [tableDataW-1:0]sqTable[0:tableL-1];
genvar gi;
generate 
	for(gi=0;gi<tableL;gi=gi+1)begin:tableLoop
			assign sqTable[gi]=sqTableS[FixTableBitW*(gi*(FixTableMax-1)/(tableL-1))+:FixTableBitW]*tableDataMax/FixTableMax;
			//(gi**power)*tableDataMax/((tableL-1)**power);
	end
endgenerate

wire outSign=in1[dataW-1]^in2[dataW-1];
wire [dataW-2:0]absIn1=(in1[dataW-1])?-in1:in1;
wire [dataW-2:0]absIn2=(in2[dataW-1])?-in2:in2;
wire [dataW-2:0]minAbs=(absIn1<absIn2)?absIn1:absIn2;


wire [outW-1-1:0]outDataAbs=sqTable[minAbs];
assign outData=(outSign)?-outDataAbs:outDataAbs;

endmodule

For Simulate/exp/wave.vcd
$date
	Tue Apr 07 23:14:15 2015
$end
$version
	Icarus Verilog
$end
$timescale
	1s
$end
$scope module ABSData $end
$var wire 8 ! in [7:0] $end
$var wire 7 " outData [6:0] $end
$upscope $end
$scope module test $end
$var wire 1 # XZZ $end
$var reg 1 $ clk $end
$var reg 8 % counter [7:0] $end
$scope module xm $end
$var wire 7 & absIn1 [6:0] $end
$var wire 7 ' absIn2 [6:0] $end
$var wire 8 ( in1 [7:0] $end
$var wire 8 ) in2 [7:0] $end
$var wire 7 * minAbs [6:0] $end
$var wire 8 + outData [7:0] $end
$var wire 7 , outDataAbs [6:0] $end
$var wire 1 - outSign $end
$var wire 896 . sqTableS [895:0] $end
$scope begin tableLoop[0] $end
$upscope $end
$scope begin tableLoop[1] $end
$upscope $end
$scope begin tableLoop[2] $end
$upscope $end
$scope begin tableLoop[3] $end
$upscope $end
$scope begin tableLoop[4] $end
$upscope $end
$scope begin tableLoop[5] $end
$upscope $end
$scope begin tableLoop[6] $end
$upscope $end
$scope begin tableLoop[7] $end
$upscope $end
$scope begin tableLoop[8] $end
$upscope $end
$scope begin tableLoop[9] $end
$upscope $end
$scope begin tableLoop[10] $end
$upscope $end
$scope begin tableLoop[11] $end
$upscope $end
$scope begin tableLoop[12] $end
$upscope $end
$scope begin tableLoop[13] $end
$upscope $end
$scope begin tableLoop[14] $end
$upscope $end
$scope begin tableLoop[15] $end
$upscope $end
$scope begin tableLoop[16] $end
$upscope $end
$scope begin tableLoop[17] $end
$upscope $end
$scope begin tableLoop[18] $end
$upscope $end
$scope begin tableLoop[19] $end
$upscope $end
$scope begin tableLoop[20] $end
$upscope $end
$scope begin tableLoop[21] $end
$upscope $end
$scope begin tableLoop[22] $end
$upscope $end
$scope begin tableLoop[23] $end
$upscope $end
$scope begin tableLoop[24] $end
$upscope $end
$scope begin tableLoop[25] $end
$upscope $end
$scope begin tableLoop[26] $end
$upscope $end
$scope begin tableLoop[27] $end
$upscope $end
$scope begin tableLoop[28] $end
$upscope $end
$scope begin tableLoop[29] $end
$upscope $end
$scope begin tableLoop[30] $end
$upscope $end
$scope begin tableLoop[31] $end
$upscope $end
$scope begin tableLoop[32] $end
$upscope $end
$scope begin tableLoop[33] $end
$upscope $end
$scope begin tableLoop[34] $end
$upscope $end
$scope begin tableLoop[35] $end
$upscope $end
$scope begin tableLoop[36] $end
$upscope $end
$scope begin tableLoop[37] $end
$upscope $end
$scope begin tableLoop[38] $end
$upscope $end
$scope begin tableLoop[39] $end
$upscope $end
$scope begin tableLoop[40] $end
$upscope $end
$scope begin tableLoop[41] $end
$upscope $end
$scope begin tableLoop[42] $end
$upscope $end
$scope begin tableLoop[43] $end
$upscope $end
$scope begin tableLoop[44] $end
$upscope $end
$scope begin tableLoop[45] $end
$upscope $end
$scope begin tableLoop[46] $end
$upscope $end
$scope begin tableLoop[47] $end
$upscope $end
$scope begin tableLoop[48] $end
$upscope $end
$scope begin tableLoop[49] $end
$upscope $end
$scope begin tableLoop[50] $end
$upscope $end
$scope begin tableLoop[51] $end
$upscope $end
$scope begin tableLoop[52] $end
$upscope $end
$scope begin tableLoop[53] $end
$upscope $end
$scope begin tableLoop[54] $end
$upscope $end
$scope begin tableLoop[55] $end
$upscope $end
$scope begin tableLoop[56] $end
$upscope $end
$scope begin tableLoop[57] $end
$upscope $end
$scope begin tableLoop[58] $end
$upscope $end
$scope begin tableLoop[59] $end
$upscope $end
$scope begin tableLoop[60] $end
$upscope $end
$scope begin tableLoop[61] $end
$upscope $end
$scope begin tableLoop[62] $end
$upscope $end
$scope begin tableLoop[63] $end
$upscope $end
$scope begin tableLoop[64] $end
$upscope $end
$scope begin tableLoop[65] $end
$upscope $end
$scope begin tableLoop[66] $end
$upscope $end
$scope begin tableLoop[67] $end
$upscope $end
$scope begin tableLoop[68] $end
$upscope $end
$scope begin tableLoop[69] $end
$upscope $end
$scope begin tableLoop[70] $end
$upscope $end
$scope begin tableLoop[71] $end
$upscope $end
$scope begin tableLoop[72] $end
$upscope $end
$scope begin tableLoop[73] $end
$upscope $end
$scope begin tableLoop[74] $end
$upscope $end
$scope begin tableLoop[75] $end
$upscope $end
$scope begin tableLoop[76] $end
$upscope $end
$scope begin tableLoop[77] $end
$upscope $end
$scope begin tableLoop[78] $end
$upscope $end
$scope begin tableLoop[79] $end
$upscope $end
$scope begin tableLoop[80] $end
$upscope $end
$scope begin tableLoop[81] $end
$upscope $end
$scope begin tableLoop[82] $end
$upscope $end
$scope begin tableLoop[83] $end
$upscope $end
$scope begin tableLoop[84] $end
$upscope $end
$scope begin tableLoop[85] $end
$upscope $end
$scope begin tableLoop[86] $end
$upscope $end
$scope begin tableLoop[87] $end
$upscope $end
$scope begin tableLoop[88] $end
$upscope $end
$scope begin tableLoop[89] $end
$upscope $end
$scope begin tableLoop[90] $end
$upscope $end
$scope begin tableLoop[91] $end
$upscope $end
$scope begin tableLoop[92] $end
$upscope $end
$scope begin tableLoop[93] $end
$upscope $end
$scope begin tableLoop[94] $end
$upscope $end
$scope begin tableLoop[95] $end
$upscope $end
$scope begin tableLoop[96] $end
$upscope $end
$scope begin tableLoop[97] $end
$upscope $end
$scope begin tableLoop[98] $end
$upscope $end
$scope begin tableLoop[99] $end
$upscope $end
$scope begin tableLoop[100] $end
$upscope $end
$scope begin tableLoop[101] $end
$upscope $end
$scope begin tableLoop[102] $end
$upscope $end
$scope begin tableLoop[103] $end
$upscope $end
$scope begin tableLoop[104] $end
$upscope $end
$scope begin tableLoop[105] $end
$upscope $end
$scope begin tableLoop[106] $end
$upscope $end
$scope begin tableLoop[107] $end
$upscope $end
$scope begin tableLoop[108] $end
$upscope $end
$scope begin tableLoop[109] $end
$upscope $end
$scope begin tableLoop[110] $end
$upscope $end
$scope begin tableLoop[111] $end
$upscope $end
$scope begin tableLoop[112] $end
$upscope $end
$scope begin tableLoop[113] $end
$upscope $end
$scope begin tableLoop[114] $end
$upscope $end
$scope begin tableLoop[115] $end
$upscope $end
$scope begin tableLoop[116] $end
$upscope $end
$scope begin tableLoop[117] $end
$upscope $end
$scope begin tableLoop[118] $end
$upscope $end
$scope begin tableLoop[119] $end
$upscope $end
$scope begin tableLoop[120] $end
$upscope $end
$scope begin tableLoop[121] $end
$upscope $end
$scope begin tableLoop[122] $end
$upscope $end
$scope begin tableLoop[123] $end
$upscope $end
$scope begin tableLoop[124] $end
$upscope $end
$scope begin tableLoop[125] $end
$upscope $end
$scope begin tableLoop[126] $end
$upscope $end
$scope begin tableLoop[127] $end
$upscope $end
$upscope $end
$upscope $end
$enddefinitions $end
#0
$dumpvars
b11111111111111111111111111111111111111111111111111111111111111111111111111111111111111111111111111111111111111111111111111111111111111111111111111111111111111111111111111111111111111111111111111111111111111111111111101111110111111011111101111110111110111111011111101111110011111001111011111101111110101111001111100011101111110110111010111101001110010111000011011111101101110101111010001100110110001111000011011110101101110110001010100101000110011101001010100011110000110111111011110001110000110101011000101011100101011010011101001000100001001111000111000011001001011100101000010010001000000011110001101000101100010100001001000100000001110000110000010100001000000100000001100000110000010000001000000100000001000000100000010000001000000100000000000000000000000000000000000000000000000000000000000000000000000000000000000000000000000000000000000000000000000000000000000000000000000000000000000000000 .
0-
b0 ,
b0 +
b0 *
b1111111 )
b0 (
b1111111 '
b0 &
b0 %
0$
0#
bx "
bz !
$end
#5
b1 *
b1 &
b1 %
b1 (
1$
#10
0$
#15
b10 *
b10 &
b10 %
b10 (
1$
#20
0$
#25
b11 *
b11 &
b11 %
b11 (
1$
#30
0$
#35
b100 *
b100 &
b100 %
b100 (
1$
#40
0$
#45
b101 *
b101 &
b101 %
b101 (
1$
#50
0$
#55
b110 *
b110 &
b110 %
b110 (
1$
#60
0$
#65
b111 *
b111 &
b111 %
b111 (
1$
#70
0$
#75
b1000 *
b1000 &
b1000 %
b1000 (
1$
#80
0$
#85
b1001 *
b1001 &
b1001 %
b1001 (
1$
#90
0$
#95
b1010 *
b1010 &
b1010 %
b1010 (
1$
#100
0$
#105
b1011 *
b1011 &
b1011 %
b1011 (
1$
#110
0$
#115
b1100 *
b1100 &
b1100 %
b1100 (
1$
#120
0$
#125
b1101 *
b1101 &
b1101 %
b1101 (
1$
#130
0$
#135
b1110 *
b1110 &
b1110 %
b1110 (
1$
#140
0$
#145
b1111 *
b1111 &
b1111 %
b1111 (
1$
#150
0$
#155
b10000 *
b10000 &
b10000 %
b10000 (
1$
#160
0$
#165
b10001 *
b10001 &
b10001 %
b10001 (
1$
#170
0$
#175
b10010 *
b10010 &
b10010 %
b10010 (
1$
#180
0$
#185
b10011 *
b10011 &
b10011 %
b10011 (
1$
#190
0$
#195
b10100 *
b10100 &
b10100 %
b10100 (
1$
#200
0$
#205
b10101 *
b10101 &
b10101 %
b10101 (
1$
#210
0$
#215
b10110 *
b10110 &
b10110 %
b10110 (
1$
#220
0$
#225
b10111 *
b10111 &
b10111 %
b10111 (
1$
#230
0$
#235
1#
b1 +
b1 ,
b11000 *
b11000 &
b11000 %
b11000 (
1$
#240
0$
#245
b11001 *
b11001 &
b11001 %
b11001 (
1$
#250
0$
#255
b11010 *
b11010 &
b11010 %
b11010 (
1$
#260
0$
#265
b11011 *
b11011 &
b11011 %
b11011 (
1$
#270
0$
#275
b11100 *
b11100 &
b11100 %
b11100 (
1$
#280
0$
#285
0#
b10 +
b10 ,
b11101 *
b11101 &
b11101 %
b11101 (
1$
#290
0$
#295
b11110 *
b11110 &
b11110 %
b11110 (
1$
#300
0$
#305
b11111 *
b11111 &
b11111 %
b11111 (
1$
#310
0$
#315
1#
b11 +
b11 ,
b100000 *
b100000 &
b100000 %
b100000 (
1$
#320
0$
#325
b100001 *
b100001 &
b100001 %
b100001 (
1$
#330
0$
#335
0#
b100 +
b100 ,
b100010 *
b100010 &
b100010 %
b100010 (
1$
#340
0$
#345
b100011 *
b100011 &
b100011 %
b100011 (
1$
#350
0$
#355
1#
b101 +
b101 ,
b100100 *
b100100 &
b100100 %
b100100 (
1$
#360
0$
#365
0#
b110 +
b110 ,
b100101 *
b100101 &
b100101 %
b100101 (
1$
#370
0$
#375
1#
b111 +
b111 ,
b100110 *
b100110 &
b100110 %
b100110 (
1$
#380
0$
#385
0#
b1000 +
b1000 ,
b100111 *
b100111 &
b100111 %
b100111 (
1$
#390
0$
#395
1#
b1001 +
b1001 ,
b101000 *
b101000 &
b101000 %
b101000 (
1$
#400
0$
#405
0#
b1010 +
b1010 ,
b101001 *
b101001 &
b101001 %
b101001 (
1$
#410
0$
#415
1#
b1011 +
b1011 ,
b101010 *
b101010 &
b101010 %
b101010 (
1$
#420
0$
#425
b1101 +
b1101 ,
b101011 *
b101011 &
b101011 %
b101011 (
1$
#430
0$
#435
b1111 +
b1111 ,
b101100 *
b101100 &
b101100 %
b101100 (
1$
#440
0$
#445
0#
b10000 +
b10000 ,
b101101 *
b101101 &
b101101 %
b101101 (
1$
#450
0$
#455
b10010 +
b10010 ,
b101110 *
b101110 &
b101110 %
b101110 (
1$
#460
0$
#465
b10100 +
b10100 ,
b101111 *
b101111 &
b101111 %
b101111 (
1$
#470
0$
#475
1#
b10111 +
b10111 ,
b110000 *
b110000 &
b110000 %
b110000 (
1$
#480
0$
#485
b11001 +
b11001 ,
b110001 *
b110001 &
b110001 %
b110001 (
1$
#490
0$
#495
0#
b11100 +
b11100 ,
b110010 *
b110010 &
b110010 %
b110010 (
1$
#500
0$
#505
b11110 +
b11110 ,
b110011 *
b110011 &
b110011 %
b110011 (
1$
#510
0$
#515
1#
b100001 +
b100001 ,
b110100 *
b110100 &
b110100 %
b110100 (
1$
#520
0$
#525
0#
b100100 +
b100100 ,
b110101 *
b110101 &
b110101 %
b110101 (
1$
#530
0$
#535
1#
b100111 +
b100111 ,
b110110 *
b110110 &
b110110 %
b110110 (
1$
#540
0$
#545
b101011 +
b101011 ,
b110111 *
b110111 &
b110111 %
b110111 (
1$
#550
0$
#555
0#
b101110 +
b101110 ,
b111000 *
b111000 &
b111000 %
b111000 (
1$
#560
0$
#565
1#
b110001 +
b110001 ,
b111001 *
b111001 &
b111001 %
b111001 (
1$
#570
0$
#575
b110101 +
b110101 ,
b111010 *
b111010 &
b111010 %
b111010 (
1$
#580
0$
#585
0#
b111000 +
b111000 ,
b111011 *
b111011 &
b111011 %
b111011 (
1$
#590
0$
#595
b111100 +
b111100 ,
b111100 *
b111100 &
b111100 %
b111100 (
1$
#600
0$
#605
1#
b111111 +
b111111 ,
b111101 *
b111101 &
b111101 %
b111101 (
1$
#610
0$
#615
b1000011 +
b1000011 ,
b111110 *
b111110 &
b111110 %
b111110 (
1$
#620
0$
#625
b1000111 +
b1000111 ,
b111111 *
b111111 &
b111111 %
b111111 (
1$
#630
0$
#635
0#
b1001010 +
b1001010 ,
b1000000 *
b1000000 &
b1000000 %
b1000000 (
1$
#640
0$
#645
b1001110 +
b1001110 ,
b1000001 *
b1000001 &
b1000001 %
b1000001 (
1$
#650
0$
#655
1#
b1010001 +
b1010001 ,
b1000010 *
b1000010 &
b1000010 %
b1000010 (
1$
#660
0$
#665
0#
b1010100 +
b1010100 ,
b1000011 *
b1000011 &
b1000011 %
b1000011 (
1$
#670
0$
#675
b1011000 +
b1011000 ,
b1000100 *
b1000100 &
b1000100 %
b1000100 (
1$
#680
0$
#685
1#
b1011011 +
b1011011 ,
b1000101 *
b1000101 &
b1000101 %
b1000101 (
1$
#690
0$
#695
0#
b1011110 +
b1011110 ,
b1000110 *
b1000110 &
b1000110 %
b1000110 (
1$
#700
0$
#705
1#
b1100001 +
b1100001 ,
b1000111 *
b1000111 &
b1000111 %
b1000111 (
1$
#710
0$
#715
b1100011 +
b1100011 ,
b1001000 *
b1001000 &
b1001000 %
b1001000 (
1$
#720
0$
#725
0#
b1100110 +
b1100110 ,
b1001001 *
b1001001 &
b1001001 %
b1001001 (
1$
#730
0$
#735
b1101000 +
b1101000 ,
b1001010 *
b1001010 &
b1001010 %
b1001010 (
1$
#740
0$
#745
1#
b1101011 +
b1101011 ,
b1001011 *
b1001011 &
b1001011 %
b1001011 (
1$
#750
0$
#755
b1101101 +
b1101101 ,
b1001100 *
b1001100 &
b1001100 %
b1001100 (
1$
#760
0$
#765
b1101111 +
b1101111 ,
b1001101 *
b1001101 &
b1001101 %
b1001101 (
1$
#770
0$
#775
0#
b1110000 +
b1110000 ,
b1001110 *
b1001110 &
b1001110 %
b1001110 (
1$
#780
0$
#785
b1110010 +
b1110010 ,
b1001111 *
b1001111 &
b1001111 %
b1001111 (
1$
#790
0$
#795
b1110100 +
b1110100 ,
b1010000 *
b1010000 &
b1010000 %
b1010000 (
1$
#800
0$
#805
1#
b1110101 +
b1110101 ,
b1010001 *
b1010001 &
b1010001 %
b1010001 (
1$
#810
0$
#815
0#
b1110110 +
b1110110 ,
b1010010 *
b1010010 &
b1010010 %
b1010010 (
1$
#820
0$
#825
1#
b1110111 +
b1110111 ,
b1010011 *
b1010011 &
b1010011 %
b1010011 (
1$
#830
0$
#835
0#
b1111000 +
b1111000 ,
b1010100 *
b1010100 &
b1010100 %
b1010100 (
1$
#840
0$
#845
1#
b1111001 +
b1111001 ,
b1010101 *
b1010101 &
b1010101 %
b1010101 (
1$
#850
0$
#855
0#
b1111010 +
b1111010 ,
b1010110 *
b1010110 &
b1010110 %
b1010110 (
1$
#860
0$
#865
1#
b1111011 +
b1111011 ,
b1010111 *
b1010111 &
b1010111 %
b1010111 (
1$
#870
0$
#875
b1011000 *
b1011000 &
b1011000 %
b1011000 (
1$
#880
0$
#885
0#
b1111100 +
b1111100 ,
b1011001 *
b1011001 &
b1011001 %
b1011001 (
1$
#890
0$
#895
b1011010 *
b1011010 &
b1011010 %
b1011010 (
1$
#900
0$
#905
1#
b1111101 +
b1111101 ,
b1011011 *
b1011011 &
b1011011 %
b1011011 (
1$
#910
0$
#915
b1011100 *
b1011100 &
b1011100 %
b1011100 (
1$
#920
0$
#925
b1011101 *
b1011101 &
b1011101 %
b1011101 (
1$
#930
0$
#935
0#
b1111110 +
b1111110 ,
b1011110 *
b1011110 &
b1011110 %
b1011110 (
1$
#940
0$
#945
b1011111 *
b1011111 &
b1011111 %
b1011111 (
1$
#950
0$
#955
b1100000 *
b1100000 &
b1100000 %
b1100000 (
1$
#960
0$
#965
b1100001 *
b1100001 &
b1100001 %
b1100001 (
1$
#970
0$
#975
b1100010 *
b1100010 &
b1100010 %
b1100010 (
1$
#980
0$
#985
1#
b1111111 +
b1111111 ,
b1100011 *
b1100011 &
b1100011 %
b1100011 (
1$
#990
0$
#995
b1100100 *
b1100100 &
b1100100 %
b1100100 (
1$
#1000
0$
#1005
b1100101 *
b1100101 &
b1100101 %
b1100101 (
1$
#1010
0$
#1015
b1100110 *
b1100110 &
b1100110 %
b1100110 (
1$
#1020
0$
#1025
b1100111 *
b1100111 &
b1100111 %
b1100111 (
1$
#1030
0$
#1035
b1101000 *
b1101000 &
b1101000 %
b1101000 (
1$
#1040
0$
#1045
b1101001 *
b1101001 &
b1101001 %
b1101001 (
1$
#1050
0$
#1055
b1101010 *
b1101010 &
b1101010 %
b1101010 (
1$
#1060
0$
#1065
b1101011 *
b1101011 &
b1101011 %
b1101011 (
1$
#1070
0$
#1075
b1101100 *
b1101100 &
b1101100 %
b1101100 (
1$
#1080
0$
#1085
b1101101 *
b1101101 &
b1101101 %
b1101101 (
1$
#1090
0$
#1095
b1101110 *
b1101110 &
b1101110 %
b1101110 (
1$
#1100
0$
#1105
b1101111 *
b1101111 &
b1101111 %
b1101111 (
1$
#1110
0$
#1115
b1110000 *
b1110000 &
b1110000 %
b1110000 (
1$
#1120
0$
#1125
b1110001 *
b1110001 &
b1110001 %
b1110001 (
1$
#1130
0$
#1135
b1110010 *
b1110010 &
b1110010 %
b1110010 (
1$
#1140
0$
#1145
b1110011 *
b1110011 &
b1110011 %
b1110011 (
1$
#1150
0$
#1155
b1110100 *
b1110100 &
b1110100 %
b1110100 (
1$
#1160
0$
#1165
b1110101 *
b1110101 &
b1110101 %
b1110101 (
1$
#1170
0$
#1175
b1110110 *
b1110110 &
b1110110 %
b1110110 (
1$
#1180
0$
#1185
b1110111 *
b1110111 &
b1110111 %
b1110111 (
1$
#1190
0$
#1195
b1111000 *
b1111000 &
b1111000 %
b1111000 (
1$
#1200
0$
#1205
b1111001 *
b1111001 &
b1111001 %
b1111001 (
1$
#1210
0$
#1215
b1111010 *
b1111010 &
b1111010 %
b1111010 (
1$
#1220
0$
#1225
b1111011 *
b1111011 &
b1111011 %
b1111011 (
1$
#1230
0$
#1235
b1111100 *
b1111100 &
b1111100 %
b1111100 (
1$
#1240
0$
#1245
b1111101 *
b1111101 &
b1111101 %
b1111101 (
1$
#1250
0$
#1255
b1111110 *
b1111110 &
b1111110 %
b1111110 (
1$
#1260
0$
#1265
b1111111 *
b1111111 &
b1111111 %
b1111111 (
1$
#1270
0$
#1275
0#
b0 +
b0 ,
b0 *
1-
b0 &
b10000000 %
b10000000 (
1$
#1280
0$
#1285
1#
b10000001 +
b1111111 ,
b1111111 *
b1111111 &
b10000001 %
b10000001 (
1$
#1290
0$
#1295
b1111110 *
b1111110 &
b10000010 %
b10000010 (
1$
#1300
0$
#1305
b1111101 *
b1111101 &
b10000011 %
b10000011 (
1$
#1310
0$
#1315
b1111100 *
b1111100 &
b10000100 %
b10000100 (
1$
#1320
0$
#1325
b1111011 *
b1111011 &
b10000101 %
b10000101 (
1$
#1330
0$
#1335
b1111010 *
b1111010 &
b10000110 %
b10000110 (
1$
#1340
0$
#1345
b1111001 *
b1111001 &
b10000111 %
b10000111 (
1$
#1350
0$
#1355
b1111000 *
b1111000 &
b10001000 %
b10001000 (
1$
#1360
0$
#1365
b1110111 *
b1110111 &
b10001001 %
b10001001 (
1$
#1370
0$
#1375
b1110110 *
b1110110 &
b10001010 %
b10001010 (
1$
#1380
0$
#1385
b1110101 *
b1110101 &
b10001011 %
b10001011 (
1$
#1390
0$
#1395
b1110100 *
b1110100 &
b10001100 %
b10001100 (
1$
#1400
0$
#1405
b1110011 *
b1110011 &
b10001101 %
b10001101 (
1$
#1410
0$
#1415
b1110010 *
b1110010 &
b10001110 %
b10001110 (
1$
#1420
0$
#1425
b1110001 *
b1110001 &
b10001111 %
b10001111 (
1$
#1430
0$
#1435
b1110000 *
b1110000 &
b10010000 %
b10010000 (
1$
#1440
0$
#1445
b1101111 *
b1101111 &
b10010001 %
b10010001 (
1$
#1450
0$
#1455
b1101110 *
b1101110 &
b10010010 %
b10010010 (
1$
#1460
0$
#1465
b1101101 *
b1101101 &
b10010011 %
b10010011 (
1$
#1470
0$
#1475
b1101100 *
b1101100 &
b10010100 %
b10010100 (
1$
#1480
0$
#1485
b1101011 *
b1101011 &
b10010101 %
b10010101 (
1$
#1490
0$
#1495
b1101010 *
b1101010 &
b10010110 %
b10010110 (
1$
#1500
0$
#1505
b1101001 *
b1101001 &
b10010111 %
b10010111 (
1$
#1510
0$
#1515
b1101000 *
b1101000 &
b10011000 %
b10011000 (
1$
#1520
0$
#1525
b1100111 *
b1100111 &
b10011001 %
b10011001 (
1$
#1530
0$
#1535
b1100110 *
b1100110 &
b10011010 %
b10011010 (
1$
#1540
0$
#1545
b1100101 *
b1100101 &
b10011011 %
b10011011 (
1$
#1550
0$
#1555
b1100100 *
b1100100 &
b10011100 %
b10011100 (
1$
#1560
0$
#1565
b1100011 *
b1100011 &
b10011101 %
b10011101 (
1$
#1570
0$
#1575
0#
b10000010 +
b1111110 ,
b1100010 *
b1100010 &
b10011110 %
b10011110 (
1$
#1580
0$
#1585
b1100001 *
b1100001 &
b10011111 %
b10011111 (
1$
#1590
0$
#1595
b1100000 *
b1100000 &
b10100000 %
b10100000 (
1$
#1600
0$
#1605
b1011111 *
b1011111 &
b10100001 %
b10100001 (
1$
#1610
0$
#1615
b1011110 *
b1011110 &
b10100010 %
b10100010 (
1$
#1620
0$
#1625
1#
b10000011 +
b1111101 ,
b1011101 *
b1011101 &
b10100011 %
b10100011 (
1$
#1630
0$
#1635
b1011100 *
b1011100 &
b10100100 %
b10100100 (
1$
#1640
0$
#1645
b1011011 *
b1011011 &
b10100101 %
b10100101 (
1$
#1650
0$
#1655
0#
b10000100 +
b1111100 ,
b1011010 *
b1011010 &
b10100110 %
b10100110 (
1$
#1660
0$
#1665
b1011001 *
b1011001 &
b10100111 %
b10100111 (
1$
#1670
0$
#1675
1#
b10000101 +
b1111011 ,
b1011000 *
b1011000 &
b10101000 %
b10101000 (
1$
#1680
0$
#1685
b1010111 *
b1010111 &
b10101001 %
b10101001 (
1$
#1690
0$
#1695
0#
b10000110 +
b1111010 ,
b1010110 *
b1010110 &
b10101010 %
b10101010 (
1$
#1700
0$
#1705
1#
b10000111 +
b1111001 ,
b1010101 *
b1010101 &
b10101011 %
b10101011 (
1$
#1710
0$
#1715
0#
b10001000 +
b1111000 ,
b1010100 *
b1010100 &
b10101100 %
b10101100 (
1$
#1720
0$
#1725
1#
b10001001 +
b1110111 ,
b1010011 *
b1010011 &
b10101101 %
b10101101 (
1$
#1730
0$
#1735
0#
b10001010 +
b1110110 ,
b1010010 *
b1010010 &
b10101110 %
b10101110 (
1$
#1740
0$
#1745
1#
b10001011 +
b1110101 ,
b1010001 *
b1010001 &
b10101111 %
b10101111 (
1$
#1750
0$
#1755
0#
b10001100 +
b1110100 ,
b1010000 *
b1010000 &
b10110000 %
b10110000 (
1$
#1760
0$
#1765
b10001110 +
b1110010 ,
b1001111 *
b1001111 &
b10110001 %
b10110001 (
1$
#1770
0$
#1775
b10010000 +
b1110000 ,
b1001110 *
b1001110 &
b10110010 %
b10110010 (
1$
#1780
0$
#1785
1#
b10010001 +
b1101111 ,
b1001101 *
b1001101 &
b10110011 %
b10110011 (
1$
#1790
0$
#1795
b10010011 +
b1101101 ,
b1001100 *
b1001100 &
b10110100 %
b10110100 (
1$
#1800
0$
#1805
b10010101 +
b1101011 ,
b1001011 *
b1001011 &
b10110101 %
b10110101 (
1$
#1810
0$
#1815
0#
b10011000 +
b1101000 ,
b1001010 *
b1001010 &
b10110110 %
b10110110 (
1$
#1820
0$
#1825
b10011010 +
b1100110 ,
b1001001 *
b1001001 &
b10110111 %
b10110111 (
1$
#1830
0$
#1835
1#
b10011101 +
b1100011 ,
b1001000 *
b1001000 &
b10111000 %
b10111000 (
1$
#1840
0$
#1845
b10011111 +
b1100001 ,
b1000111 *
b1000111 &
b10111001 %
b10111001 (
1$
#1850
0$
#1855
0#
b10100010 +
b1011110 ,
b1000110 *
b1000110 &
b10111010 %
b10111010 (
1$
#1860
0$
#1865
1#
b10100101 +
b1011011 ,
b1000101 *
b1000101 &
b10111011 %
b10111011 (
1$
#1870
0$
#1875
0#
b10101000 +
b1011000 ,
b1000100 *
b1000100 &
b10111100 %
b10111100 (
1$
#1880
0$
#1885
b10101100 +
b1010100 ,
b1000011 *
b1000011 &
b10111101 %
b10111101 (
1$
#1890
0$
#1895
1#
b10101111 +
b1010001 ,
b1000010 *
b1000010 &
b10111110 %
b10111110 (
1$
#1900
0$
#1905
0#
b10110010 +
b1001110 ,
b1000001 *
b1000001 &
b10111111 %
b10111111 (
1$
#1910
0$
#1915
b10110110 +
b1001010 ,
b1000000 *
b1000000 &
b11000000 %
b11000000 (
1$
#1920
0$
#1925
1#
b10111001 +
b1000111 ,
b111111 *
b111111 &
b11000001 %
b11000001 (
1$
#1930
0$
#1935
b10111101 +
b1000011 ,
b111110 *
b111110 &
b11000010 %
b11000010 (
1$
#1940
0$
#1945
b11000001 +
b111111 ,
b111101 *
b111101 &
b11000011 %
b11000011 (
1$
#1950
0$
#1955
0#
b11000100 +
b111100 ,
b111100 *
b111100 &
b11000100 %
b11000100 (
1$
#1960
0$
#1965
b11001000 +
b111000 ,
b111011 *
b111011 &
b11000101 %
b11000101 (
1$
#1970
0$
#1975
1#
b11001011 +
b110101 ,
b111010 *
b111010 &
b11000110 %
b11000110 (
1$
#1980
0$
#1985
b11001111 +
b110001 ,
b111001 *
b111001 &
b11000111 %
b11000111 (
1$
#1990
0$
#1995
0#
b11010010 +
b101110 ,
b111000 *
b111000 &
b11001000 %
b11001000 (
1$
#2000
0$
#2005
1#
b11010101 +
b101011 ,
b110111 *
b110111 &
b11001001 %
b11001001 (
1$
#2010
0$
#2015
b11011001 +
b100111 ,
b110110 *
b110110 &
b11001010 %
b11001010 (
1$
#2020
0$
#2025
0#
b11011100 +
b100100 ,
b110101 *
b110101 &
b11001011 %
b11001011 (
1$
#2030
0$
#2035
1#
b11011111 +
b100001 ,
b110100 *
b110100 &
b11001100 %
b11001100 (
1$
#2040
0$
